rustfst_python-1.2.6.dist-info/RECORD
rustfst_python-1.2.6.dist-info/WHEEL
rustfst_python-1.2.6.dist-info/top_level.txt
rustfst_python-1.2.6.dist-info/METADATA
rustfst/string_paths_iterator.py
rustfst/symbol_table.py
rustfst/trs.py
rustfst/ffi_utils.py
rustfst/__init__.py
rustfst/weight.py
rustfst/drawing_config.py
rustfst/tr.py
rustfst/iterators.py
rustfst/py.typed
rustfst/string_path.py
rustfst/_rustfst_python.cpython-313-darwin.so
rustfst/algorithms/inversion.py
rustfst/algorithms/optimize.py
rustfst/algorithms/determinize.py
rustfst/algorithms/compose.py
rustfst/algorithms/top_sort.py
rustfst/algorithms/connect.py
rustfst/algorithms/concat.py
rustfst/algorithms/tr_sort.py
rustfst/algorithms/reverse.py
rustfst/algorithms/shortest_path.py
rustfst/algorithms/__init__.py
rustfst/algorithms/minimize.py
rustfst/algorithms/isomorphic.py
rustfst/algorithms/randgen.py
rustfst/algorithms/rm_epsilon.py
rustfst/algorithms/tr_unique.py
rustfst/algorithms/project.py
rustfst/algorithms/union.py
rustfst/algorithms/replace.py
rustfst/fst/__init__.py
rustfst/fst/const_fst.py
rustfst/fst/vector_fst.py
