Metadata-Version: 2.4
Name: rustfst-python
Version: 1.2.6
Summary: Python bindings for RustFST
Author-email: Alexandre Caulier <alexandre.caulier.a@gmail.com>
License: MIT OR Apache-2.0
Classifier: Development Status :: 3 - Alpha
Classifier: Intended Audience :: Developers
Classifier: Programming Language :: Python :: 3
Classifier: Programming Language :: Python :: 3.7
Classifier: Programming Language :: Python :: 3.8
Classifier: Programming Language :: Python :: 3.9
Classifier: Programming Language :: Python :: 3.10
Classifier: Programming Language :: Python :: 3.11
Classifier: Programming Language :: Python :: 3.13
Classifier: Programming Language :: Rust
Requires-Python: <3.14,>=3.13
Requires-Dist: patchelf>=0.17; sys_platform == "linux"
Provides-Extra: dev
Requires-Dist: pytest>=7.0.0; extra == "dev"
Requires-Dist: ruff>=0.7.0; extra == "dev"
Provides-Extra: docs
Requires-Dist: mkdocs>=1.4.0; extra == "docs"
Requires-Dist: mkdocs-material>=8.0.0; extra == "docs"
Requires-Dist: mkdocs-macros-plugin>=1.3.7; extra == "docs"
Requires-Dist: mike>=1.1.0; extra == "docs"
Requires-Dist: mkdocs-autorefs>=0.4.0; extra == "docs"
Requires-Dist: mkdocstrings[python]>=0.19.0; extra == "docs"
Requires-Dist: mkdocs-section-index>=0.3.5; extra == "docs"
